{
  "evil geniuses '19 mp5": {
    "price": 900,
    "avg-price": 1268,
    "discounted-percentage": 29,
    "roi": 1000,
    "sellers": 39,
    "buyers": 32,
    "highest-buyer": 800,
    "last_sales_string": "Last sales: 1300, 1399, 1400, 1390, 1200",
    "url": "https://www.ubisoft.com/es-es/game/rainbow-six/siege/marketplace?route=buy%2Fitem-details&itemId=ced2005b-2430-4a38-b291-64dad7e34794",
    "asset-url": "https://ubiservices.cdn.ubi.com/0d2ae42d-4c27-4cb7-af6c-2099062302bb/DeployerAssetsJune2023/722e0f63_f277_7d27_0d64_d3ec26dc2bfd.png",
    "sales-plot-path": "assets/plots/evil geniuses '19 mp5.jpg",
    "updated": 1709823066.1261897
  }
}